{"antiFeatures":{},"commandLine":["/usr/bin/fdroid update"],"disabled":[],"endTimestamp":1641532886870,"failedBuilds":{},"fdroiddata":{"commitId":"656b54b1995dd1d8a55be6864460ddc2e6056d9b","isDirty":true,"modifiedFiles":["repo/index-v1.jar","repo/index-v1.json","repo/index.jar","repo/index.xml","repo/status/running.json","repo/status/update.json"],"untrackedFiles":["config.yml","find.sh","tmp/apkcache.json"]},"noPackages":["i2p.bote.android","net.i2p.android"],"startTimestamp":1641550882000,"subcommand":"update"}